elasticSearch_collections/__init__.py
elasticSearch_collections/elasticSearch_collections.py
elasticSearch_collections/scroll_source.py
elasticSearch_collections-1.1.dist-info/LICENSE
elasticSearch_collections-1.1.dist-info/METADATA
elasticSearch_collections-1.1.dist-info/WHEEL
elasticSearch_collections-1.1.dist-info/top_level.txt
elasticSearch_collections-1.1.dist-info/RECORD
