Metadata-Version: 2.1
Name: elasticSearch-collections
Version: 1.1
Summary: Collections of ElasticSearch pyscripts for human
Home-page: https://github.com/AlexNg9527/ElasticSearchCollections
Author: Alex Ng
Author-email: alex_q_wu@qq.com
Maintainer: Alex Ng
Maintainer-email: alex_q_wu@qq.com
License: MIT
Platform: UNKNOWN
Classifier: Programming Language :: Python :: 3
License-File: LICENSE
Requires-Dist: loguru
Requires-Dist: elasticsearch (==7.11.0)
